README.md
setup.py
pwnlink/__init__.py
pwnlink/__main__.py
pwnlink.egg-info/PKG-INFO
pwnlink.egg-info/SOURCES.txt
pwnlink.egg-info/dependency_links.txt
pwnlink.egg-info/entry_points.txt
pwnlink.egg-info/requires.txt
pwnlink.egg-info/top_level.txt