Metadata-Version: 2.1
Name: pwnlink
Version: 1.2
Summary: A python3 tool for extracting admin passwords from D-link routers without authentication
Home-page: https://github.com/Ewpratten/pwnlink
Author: Evan Pratten
Author-email: ewpratten@gmail.com
License: UNKNOWN
Platform: UNKNOWN
Classifier: Programming Language :: Python :: 3
Classifier: Operating System :: OS Independent
Classifier: Development Status :: 5 - Production/Stable
